example/__init__.py
example/admin.py
example/forms.py
example/manage.py
example/models.py
example/settings.py
example/urls.py
example/views.py
example/migrations/0001_initial.py
example/migrations/__init__.py
image_cropping/__init__.py
image_cropping/admin.py
image_cropping/config.py
image_cropping/fields.py
image_cropping/thumbnail_processors.py
image_cropping/utils.py
image_cropping/widgets.py
image_cropping/backends/__init__.py
image_cropping/backends/base.py
image_cropping/backends/easy_thumbs.py
image_cropping/static/image_cropping/css/Jcrop.gif
image_cropping/static/image_cropping/css/image_cropping.css
image_cropping/static/image_cropping/css/jquery.Jcrop.css
image_cropping/static/image_cropping/css/jquery.Jcrop.min.css
image_cropping/static/image_cropping/js/dist/image_cropping.min.js
image_cropping/static/image_cropping/js/src/image_cropping.js
image_cropping/static/image_cropping/js/src/jquery.Jcrop.min.js
image_cropping/templatetags/__init__.py
image_cropping/templatetags/cropping.py
tests/__init__.py
tests/factory.py
tests/test_initialcropping.py
tests/test_processors.py
tests/test_settings.py
tests/test_templatetag.py
django_image_cropping-1.7.dist-info/LICENSE.txt
django_image_cropping-1.7.dist-info/METADATA
django_image_cropping-1.7.dist-info/WHEEL
django_image_cropping-1.7.dist-info/top_level.txt
django_image_cropping-1.7.dist-info/RECORD
